setup.py
beansontoast/__init__.py
beansontoast/main.py
beansontoast/setup.py
beansontoast.egg-info/PKG-INFO
beansontoast.egg-info/SOURCES.txt
beansontoast.egg-info/dependency_links.txt
beansontoast.egg-info/top_level.txt