Metadata-Version: 2.1
Name: beansontoast
Version: 0.1
Summary: This is a demo project with the OTC PyPI Uploader Tool!
Home-page: https://www.google.com
Author: johnbeans
Author-email: john.beans@gmail.com
Classifier: Development Status :: 5 - Production/Stable
Classifier: Intended Audience :: Developers
Classifier: Topic :: Software Development :: Build Tools
Classifier: Programming Language :: Python :: 3
Classifier: Programming Language :: Python :: 3.4
Classifier: Programming Language :: Python :: 3.5
Classifier: Programming Language :: Python :: 3.6
